magic_settings/__init__.py
magic_settings/dynamic_settings_base.py
magic_settings/special_property.py
magic_settings/utils.py
magic_settings-1.2.0.dist-info/LICENSE
magic_settings-1.2.0.dist-info/METADATA
magic_settings-1.2.0.dist-info/WHEEL
magic_settings-1.2.0.dist-info/top_level.txt
magic_settings-1.2.0.dist-info/zip-safe
magic_settings-1.2.0.dist-info/RECORD
