Metadata-Version: 2.1
Name: magic-settings
Version: 1.2.0
Summary: Configuration manager for Python applications.
Home-page: https://github.com/shocking-rodents/magic-settings/
Author: Anton Ostapenko
Author-email: olsnod@gmail.com
License: MIT
Download-URL: https://pypi.org/project/magic-settings/
Keywords: parser config environment settings configuration
Platform: UNKNOWN
Classifier: Development Status :: 5 - Production/Stable
Classifier: Intended Audience :: Developers
Classifier: License :: OSI Approved :: MIT License
Classifier: Operating System :: OS Independent
Classifier: Programming Language :: Python :: 3
Classifier: Programming Language :: Python :: 3.6
Classifier: Programming Language :: Python :: 3.7
Classifier: Programming Language :: Python :: 3.8
Classifier: Topic :: Software Development :: Libraries :: Python Modules
Classifier: Topic :: Utilities
Requires-Python: ~=3.6
Requires-Dist: python-dotenv (~=0.10.2)
Provides-Extra: yaml
Requires-Dist: PyYAML (~=5.1) ; extra == 'yaml'
